scxmatch/__init__.py
scxmatch/matching.py
scxmatch/rosenbaum.py
scxmatch-0.0.2.dist-info/METADATA
scxmatch-0.0.2.dist-info/WHEEL
scxmatch-0.0.2.dist-info/licenses/LICENSE
scxmatch-0.0.2.dist-info/RECORD
